yap_styleguide/__init__.py
yap_styleguide-0.0.2.dist-info/LICENSE
yap_styleguide-0.0.2.dist-info/WHEEL
yap_styleguide-0.0.2.dist-info/METADATA
yap_styleguide-0.0.2.dist-info/RECORD
